AUTHORS
MANIFEST.in
README.rst
setup.py
woodstock/__init__.py
woodstock/admin.py
woodstock/auth_backends.py
woodstock/default_settings.py
woodstock/forms.py
woodstock/tests.py
woodstock.egg-info/PKG-INFO
woodstock.egg-info/SOURCES.txt
woodstock.egg-info/dependency_links.txt
woodstock.egg-info/top_level.txt
woodstock/content/__init__.py
woodstock/content/event/__init__.py
woodstock/content/event/models.py
woodstock/feincms_extensions/__init__.py
woodstock/feincms_extensions/restricted_pages.py
woodstock/fixtures/salutation.json
woodstock/locale/de/LC_MESSAGES/django.mo
woodstock/locale/de/LC_MESSAGES/django.po
woodstock/locale/en/LC_MESSAGES/django.po
woodstock/locale/fr/LC_MESSAGES/django.po
woodstock/locale/it/LC_MESSAGES/django.po
woodstock/models/__init__.py
woodstock/models/attendance.py
woodstock/models/event.py
woodstock/models/event_part.py
woodstock/models/extendable.py
woodstock/models/group.py
woodstock/models/invitee.py
woodstock/models/participant.py
woodstock/models/person.py
woodstock/models/salutation.py
woodstock/templates/admin/woodstock/event/change_form.html
woodstock/templates/content/woodstock/next_events.html
woodstock/templates/woodstock/messages/view.html
woodstock/templates/woodstock/registration/activation_completed.html
woodstock/templates/woodstock/registration/change_password.html
woodstock/templates/woodstock/registration/change_userdata.html
woodstock/templates/woodstock/registration/login.html
woodstock/templates/woodstock/simple/detail.html
woodstock/templates/woodstock/simple/index.html
woodstock/templates/woodstock/simple/signup.html
woodstock/templatetags/__init__.py
woodstock/templatetags/event_tags.py
woodstock/urls/__init__.py
woodstock/urls/simple.py
woodstock/views/__init__.py
woodstock/views/decorators.py
woodstock/views/ics.py
woodstock/views/messages.py
woodstock/views/registration.py
woodstock/views/simple.py