Metadata-Version: 1.1
Name: woodstock
Version: 0.1.1
Summary: django based event toolkit
Home-page: http://github.com/allink/woodstock/
Author: Marc Egli
Author-email: egli@allink.ch
License: BSD License
Platform: OS Independent
Classifier: Development Status :: 3 - Alpha
Classifier: Environment :: Web Environment
Classifier: Framework :: Django
Classifier: Intended Audience :: Developers
Classifier: License :: OSI Approved :: BSD License
Classifier: Operating System :: OS Independent
Classifier: Programming Language :: Python
Classifier: Topic :: Internet :: WWW/HTTP :: Dynamic Content
Requires: FeinCMS(>=1.3.0)
Requires: Django(>=1.3)
Requires: pennyblack(>=0.2.1)
Requires: icalendar(>=2.1)
